Workbook

Sheet Data Agregat
A1: DATA AGREGAT BULANAN (Sumber: Superstore Sales Dataset)
A2: Baseline = rata-rata Nov 2010–Feb 2011 | Decline = rata-rata Mar–Jun 2011
A3: Catatan satuan: baris 'Sales' & 'Profit' = rata-rata PER BULAN ($). Baris 'Jumlah Pelanggan' & 'Jumlah Order' = TOTAL selama 4 bulan (bukan rata-rata bulanan).
A4: Metrik | B4: Baseline (Nov2010-Feb2011) | C4: Decline (Mar-Jun2011) | D4: Perubahan (%)
A5: Total Sales (avg/bulan, $) | B5: 302530 | C5: 261155 | D5: =(C5-B5)/B5 -> -0.1367633
A6: Jumlah Pelanggan Unik | B6: 334 | C6: 325 | D6: =(C6-B6)/B6 -> -0.026946108
A7: Jumlah Order | B7: 452 | C7: 440 | D7: =(C7-B7)/B7 -> -0.026548673
A8: Total Profit (avg/bulan, $) | B8: 23597 | C8: 30555 | D8: =(C8-B8)/B8 -> 0.29486799
A9: Rata-rata Discount Rate | B9: 0.048 | C9: 0.051 | D9: =(C9-B9)/B9 -> 0.0625
A10: Sales Wilayah Quebec (avg/bln,$) | B10: 36571 | C10: 12392 | D10: =(C10-B10)/B10 -> -0.66115228
A11: Sales Wilayah Ontario (avg/bln,$) | B11: 73253 | C11: 54811 | D11: =(C11-B11)/B11 -> -0.25175761
A12: Sales Wilayah Yukon (avg/bln,$) | B12: 35593 | C12: 21077 | D12: =(C12-B12)/B12 -> -0.407833
A13: Sales Wilayah Nunavut (avg/bln,$) | B13: 9328 | C13: 2133 | D13: =(C13-B13)/B13 -> -0.77133362
A14: Sales Kategori Office Supplies (avg/bln,$) | B14: 79210 | C14: 63344 | D14: =(C14-B14)/B14 -> -0.20030299
A15: Sales Kategori Furniture (avg/bln,$) | B15: 108538 | C15: 94369 | D15: =(C15-B15)/B15 -> -0.13054414
A16: Sales Kategori Technology (avg/bln,$) | B16: 114783 | C16: 103441 | D16: =(C16-B16)/B16 -> -0.098812542
... A18: Sales Sub-kategori Envelopes (avg/bln,$) | B18: 5605 | C18: 3188 | D18: =(C18-B18)/B18 -> -0.43122212

Sheet KPI Definition
A1: KPI DEFINITION TABLE
A2: Studi Kasus: Analisis Penurunan Penjualan — Superstore Sales Dataset
A3: Nilai Baseline/Decline & Perubahan dihitung dari sheet 'Data Agregat' via formula (bukan angka tetap)
A5: KPI | B5: Definisi | C5: Rumus | D5: Tujuan | E5: Baseline | F5: Decline | G5: Perubahan (%)
A6: Total Sales | B6: Total nilai penjualan pada periode tertentu | C6: SUM(Sales) | D6: Mengukur performa penjualan keseluruhan | E6: ='Data Agregat'!B5 -> 302530 | F6: ='Data Agregat'!C5 -> 261155 | G6: =(F6-E6)/E6 -> -0.1367633
A7: Number of Customers | B7: Jumlah pelanggan unik yang bertransaksi | C7: COUNT(DISTINCT Customer Name) | D7: Mengukur apakah penurunan berasal dari berkurangnya pelanggan | E7: ='Data Agregat'!B6 -> 334 | F7: ='Data Agregat'!C6 -> 325 | G7: =(F7-E7)/E7 -> -0.026946108
A8: Number of Orders | B8: Jumlah total transaksi/pesanan | C8: COUNT(DISTINCT Order ID) | D8: Mengukur frekuensi transaksi pelanggan | E8: ='Data Agregat'!B7 -> 452 | F8: ='Data Agregat'!C7 -> 440 | G8: =(F8-E8)/E8 -> -0.026548673
A9: Average Order Value (AOV) | B9: Rata-rata nilai per transaksi | C9: Sales / Orders | D9: Mengukur apakah nilai transaksi menurun | E9: =('Data Agregat'!B5*4)/'Data Agregat'!B7 -> 2677.2566 | F9: =('Data Agregat'!C5*4)/'Data Agregat'!C7 -> 2374.1364 | G9: =(F9-E9)/E9 -> -0.11322048
A10: Profit Margin | B10: Persentase keuntungan terhadap penjualan | C10: SUM(Profit) / SUM(Sales) | D10: Mengukur profitabilitas, bukan hanya volume | E10: ='Data Agregat'!B8/'Data Agregat'!B5 -> 0.077998876 | F10: ='Data Agregat'!C8/'Data Agregat'!C5 -> 0.11699948 | G10: =F10-E10 -> 0.039000607
A11: Discount Rate | B11: Rata-rata persentase diskon per transaksi | C11: AVG(Discount) | D11: Mengukur pengaruh diskon terhadap penurunan | E11: ='Data Agregat'!B9 -> 0.048 | F11: ='Data Agregat'!C9 -> 0.051 | G11: =(F11-E11)/E11 -> 0.0625
A12: Sales - Quebec | B12: Total penjualan wilayah Quebec | C12: SUMIFS(Sales, Region, "Quebec") | D12: Mengidentifikasi kontribusi wilayah Quebec | E12: ='Data Agregat'!B10 -> 36571 | F12: ='Data Agregat'!C10 -> 12392 | G12: =(F12-E12)/E12 -> -0.66115228
A13: Sales - Ontario | B13: Total penjualan wilayah Ontario | C13: SUMIFS(Sales, Region, "Ontario") | D13: Mengidentifikasi kontribusi wilayah Ontario | E13: ='Data Agregat'!B11 -> 73253 | F13: ='Data Agregat'!C11 -> 54811 | G13: =(F13-E13)/E13 -> -0.25175761
A14: Sales - Yukon | B14: Total penjualan wilayah Yukon | C14: SUMIFS(Sales, Region, "Yukon") | D14: Mengidentifikasi kontribusi wilayah Yukon | E14: ='Data Agregat'!B12 -> 35593 | F14: ='Data Agregat'!C12 -> 21077 | G14: =(F14-E14)/E14 -> -0.407833
A15: Sales - Nunavut | B15: Total penjualan wilayah Nunavut | C15: SUMIFS(Sales, Region, "Nunavut") | D15: Mengidentifikasi kontribusi wilayah Nunavut | E15: ='Data Agregat'!B13 -> 9328 | F15: ='Data Agregat'!C13 -> 2133 | G15: =(F15-E15)/E15 -> -0.77133362
A16: Sales - Office Supplies | B16: Total penjualan kategori Office Supplies | C16: SUMIFS(Sales, Category, "Office Supplies") | D16: Mengidentifikasi kategori penyebab penurunan | E16: ='Data Agregat'!B14 -> 79210 | F16: ='Data Agregat'!C14 -> 63344 | G16: =(F16-E16)/E16 -> -0.20030299
A17: Sales - Furniture | B17: Total penjualan kategori Furniture | C17: SUMIFS(Sales, Category, "Furniture") | D17: Mengidentifikasi kategori penyebab penurunan | E17: ='Data Agregat'!B15 -> 108538 | F17: ='Data Agregat'!C15 -> 94369 | G17: =(F17-E17)/E17 -> -0.13054414
A18: Sales - Technology | B18: Total penjualan kategori Technology | C18: SUMIFS(Sales, Category, "Technology") | D18: Mengidentifikasi kategori penyebab penurunan | E18: ='Data Agregat'!B16 -> 114783 | F18: ='Data Agregat'!C16 -> 103441 | G18: =(F18-E18)/E18 -> -0.098812542
A19: Sales - Appliances | B19: Total penjualan sub-kategori Appliances | C19: SUMIFS(Sales, SubCategory, "Appliances") | D19: Mengidentifikasi sub-kategori penyebab utama | E19: ='Data Agregat'!B17 -> 26042 | F19: ='Data Agregat'!C17 -> 9954 | G19: =(F19-E19)/E19 -> -0.61777129
A20: Sales - Envelopes | B20: Total penjualan sub-kategori Envelopes | C20: SUMIFS(Sales, SubCategory, "Envelopes") | D20: Mengidentifikasi sub-kategori penyebab utama | E20: ='Data Agregat'!B18 -> 5605 | F20: ='Data Agregat'!C18 -> 3188 | G20: =(F20-E20)/E20 -> -0.43122212
A22: INSIGHT AWAL DARI KPI
A23: - Penurunan jumlah pelanggan jauh lebih kecil dibanding penurunan AOV -> penurunan lebih disebabkan oleh menurunnya nilai transaksi, bukan hilangnya pelanggan.
A24: - Profit margin justru naik di tengah penurunan sales -> bukan masalah diskon/biaya, melainkan pergeseran komposisi produk yang terjual.
A25: - Wilayah Quebec, Ontario, Yukon, Nunavut menyumbang mayoritas penurunan -> masalah bersifat lokal, bukan menyeluruh.
